originx/__init__.py
originx/__main__.py
originx/banner.py
originx/cli.py
originx/core.py
originx/menu.py
originx/waf.py
originx/recon/__init__.py
originx/recon/base.py
originx/recon/censys.py
originx/recon/dns.py
originx/recon/favicon.py
originx/recon/otx.py
originx/recon/securitytrails.py
originx/recon/shodan.py
originx/recon/viewdns.py
originx/recon/virustotal.py
originx/utils/__init__.py
originx/utils/config.py
originx/utils/helpers.py
originx/utils/models.py
originx/verify/__init__.py
originx/verify/engine.py
originx-1.0.0.dist-info/licenses/LICENSE
originx-1.0.0.dist-info/METADATA
originx-1.0.0.dist-info/WHEEL
originx-1.0.0.dist-info/entry_points.txt
originx-1.0.0.dist-info/top_level.txt
originx-1.0.0.dist-info/RECORD
