Metadata-Version: 2.4
Name: originx
Version: 1.0.0
Summary: Professional WAF Origin IP Discovery Tool for Bug Bounty & Security Research
Author-email: LAKSHMIKANTHAN K <letchupkt.dev@gmail.com>
License-Expression: MIT
Project-URL: Homepage, https://github.com/letchupkt/originx
Project-URL: Repository, https://github.com/letchupkt/originx
Project-URL: Issues, https://github.com/letchupkt/originx/issues
Keywords: security,waf,cdn,reconnaissance,bug-bounty,origin-ip
Classifier: Development Status :: 5 - Production/Stable
Classifier: Intended Audience :: Information Technology
Classifier: Programming Language :: Python :: 3
Classifier: Programming Language :: Python :: 3.8
Classifier: Programming Language :: Python :: 3.9
Classifier: Programming Language :: Python :: 3.10
Classifier: Programming Language :: Python :: 3.11
Classifier: Topic :: Security
Classifier: Topic :: Internet :: WWW/HTTP
Requires-Python: >=3.8
License-File: LICENSE
Requires-Dist: aiohttp>=3.8.0
Requires-Dist: asyncio-throttle>=1.0.0
Requires-Dist: rich>=13.0.0
Requires-Dist: typer>=0.9.0
Requires-Dist: dnspython>=2.3.0
Requires-Dist: requests>=2.28.0
Requires-Dist: wafw00f>=2.2.0
Requires-Dist: mmh3>=3.0.0
Requires-Dist: cryptography>=3.4.0
Requires-Dist: pydantic>=1.10.0
Requires-Dist: click>=8.0.0
Provides-Extra: dev
Requires-Dist: pytest>=7.0.0; extra == "dev"
Requires-Dist: pytest-asyncio>=0.21.0; extra == "dev"
Requires-Dist: black>=22.0.0; extra == "dev"
Requires-Dist: flake8>=5.0.0; extra == "dev"
Requires-Dist: mypy>=1.0.0; extra == "dev"
Dynamic: license-file
